{
    "name": "Death Mountain Trail",
    "bgColor": "#57534e",
    "hasMQ": false,
    "locations": [
        {
            "title": "Bombable wall",
            "type": "item",
            "tags": []
        },
        {
            "title": "Song of storms grotto",
            "description": "Rock circle outside goron city",
            "type": "item",
            "tags": [
                "grotto"
            ]
        },
        {
            "title": "Great fairy at the summit",
            "type": "item",
            "tags": []
        },
        {
            "title": "Above dodongo's cavern",
            "type": "item",
            "tags": []
        },
        {
            "title": "Biggeron trade quest",
            "type": "item",
            "tags": [
                "adult"
            ]
        },
        {
            "title": "Bombable wall, near entrance",
            "type": "gs",
            "tags": []
        },
        {
            "title": "Bean patch, dodongo's cavern",
            "type": "gs",
            "tags": [
                "child",
                "bean"
            ]
        },
        {
            "title": "Hammer rock, above DC",
            "type": "gs",
            "tags": [
                "adult",
                "night"
            ]
        },
        {
            "title": "Hammer rock, path to summit",
            "type": "gs",
            "tags": [
                "adult",
                "night"
            ]
        },
        {
            "title": "Grotto heading towards summit",
            "type": "cow",
            "tags": [
                "grotto"
            ]
        },
        {
            "title": "Under rocks on ramp",
            "description": "The rupees are only there as child, but logic can require breaking the rocks as adult then returning as child.",
            "type": "rupee",
            "tags": [
                "child"
            ],
            "count": 2
        },
        {
            "title": "Cow grotto",
            "type": "rupee",
            "tags": [
                "grotto"
            ],
            "count": 11
        },
        {
            "title": "Cow grotto",
            "type": "beehive",
            "tags": [
                "grotto"
            ]
        },
        {
            "title": "Song of storms grotto",
            "description": "Rock circle outside goron city",
            "type": "beehive",
            "tags": [
                "grotto"
            ],
            "count": 2
        }
    ]
}