{
    "name": "Beneath the Well",
    "bgColor": "#3f3f46",
    "locations": [
        {
            "title": "Mirror shield chest",
            "type": "item",
            "description": "5x beans, water, big poe, milk",
            "tags": [
                "mm"
            ]
        },
        {
            "title": "Left path chest",
            "type": "item",
            "description": "Blue potion, water, bugs",
            "tags": [
                "mm"
            ]
        },
        {
            "title": "Right path chest",
            "type": "item",
            "description": "5x beans, fish, bugs",
            "tags": [
                "mm"
            ]
        },
        {
            "title": "Cow",
            "type": "mmcow",
            "description": "5x beans, 10x deku nuts, hot spring water",
            "tags": [
                "mm"
            ]
        }
    ]
}